ddsmoothing/__init__.py
ddsmoothing/certificate.py
ddsmoothing/optimization.py
ddsmoothing/optimize_dataset.py
ddsmoothing/smooth.py
ddsmoothing/utils/__init__.py
ddsmoothing/utils/datasets.py
ddsmoothing/utils/models.py
ddsmoothing/utils/resnet.py
ddsmoothing/utils/wideresnet.py
ddsmoothing_python-1.0.0.dist-info/METADATA
ddsmoothing_python-1.0.0.dist-info/WHEEL
ddsmoothing_python-1.0.0.dist-info/top_level.txt
ddsmoothing_python-1.0.0.dist-info/RECORD
