Metadata-Version: 2.1
Name: ddsmoothing-python
Version: 1.0.0
Summary: Data-dependent smoothing Python package
Home-page: https://github.com/MotasemAlfarra/Data_Dependent_Randomized_Smoothing
Author: Motasem Alfarra
Author-email: motasem.alfarra@kaust.edu.sa
License: MIT
Platform: UNKNOWN
Classifier: Programming Language :: Python :: 3
Classifier: Programming Language :: Python :: 3.7
Requires-Python: >=3.7
Requires-Dist: torch (>=1.6.0)
Requires-Dist: torchvision (>=0.7.0)
Requires-Dist: numpy (>=1.17.0)
Requires-Dist: tqdm (>=4.44.0)
Requires-Dist: scipy (>=1.5.0)
Requires-Dist: statsmodels (>=0.11.1)
